spark_betacal/__init__.py
spark_betacal/example.py
spark_betacal-0.0.3.dist-info/METADATA
spark_betacal-0.0.3.dist-info/WHEEL
spark_betacal-0.0.3.dist-info/licenses/LICENSE
spark_betacal-0.0.3.dist-info/RECORD
